Metadata-Version: 2.1
Name: bleuper
Version: 0.2
Summary: A simple lightweight library for computing BLEU scores
Home-page: https://github.com/shvms/bleuper
Author: Shuvam Shah
Author-email: shvms@outlook.com
License: MIT
Platform: UNKNOWN
Classifier: Development Status :: 3 - Alpha
Classifier: Intended Audience :: Developers
Classifier: Topic :: Scientific/Engineering :: Artificial Intelligence
Classifier: License :: OSI Approved :: MIT License
Classifier: Programming Language :: Python :: 3.5
Classifier: Programming Language :: Python :: 3.6
Classifier: Programming Language :: Python :: 3.7
Classifier: Programming Language :: Python :: 3.8
Requires-Python: >=3.5.0
